insta_profile/__init__.py
instaprofile-1.0.5.dist-info/LICENSE
instaprofile-1.0.5.dist-info/METADATA
instaprofile-1.0.5.dist-info/WHEEL
instaprofile-1.0.5.dist-info/top_level.txt
instaprofile-1.0.5.dist-info/RECORD
